{
    "540": "Categoria do instrumento",
    "215": "Tipo de Instrumento",
    "213": "Agrupamento",
    "552": "Marca e Modelo",
    "553": "Valor de aquisi\u00e7\u00e3o (R$)",
    "556": "Possui garantia?",
    "577": "Patrim\u00f4nio obrigat\u00f3rio?",
    "578": "Patrim\u00f4nio",
    "637": "Patrim\u00f4nio antigo",
    "579": "N\u00ba de s\u00e9rie",
    "580": "Deve ser calibrado?",
    "1227": "Hist\u00f3rico documental no SEI",
    "585": "Localiza\u00e7\u00e3o do instrumento",
    "586": "Respons\u00e1vel pelo instrumento",
    "632": "Tempo de utiliza\u00e7\u00e3o (dias)",
    "633": "Quantidade de reservas",
    "635": "Reservado?",
    "636": "Data de aquisi\u00e7\u00e3o",
    "549": "Acess\u00f3rios padr\u00e3o",
    "1253": "Local atual",
    "689": "Detalhamento da localiza\u00e7\u00e3o",
    "2123": "Situa\u00e7\u00e3o da calibra\u00e7\u00e3o",
    "2127": "Dias de uso em 12 meses",
    "2130": "N\u00ba de reservas em 12 meses",
    "2146": "Apelido"
}